XNAT_Dashboards-0.3.0.data/scripts/download_data.py
XNAT_Dashboards-0.3.0.data/scripts/run_dashboards.py
xnat_dashboards/__init__.py
xnat_dashboards/config.py
xnat_dashboards/app/__init__.py
xnat_dashboards/app/authentication/__init__.py
xnat_dashboards/app/authentication/controllers.py
xnat_dashboards/app/authentication/model.py
xnat_dashboards/app/dashboards/__init__.py
xnat_dashboards/app/dashboards/controllers.py
xnat_dashboards/app/dashboards/model.py
xnat_dashboards/app/static/authentication/css/main.css
xnat_dashboards/app/static/authentication/css/util.css
xnat_dashboards/app/static/authentication/js/main.js
xnat_dashboards/app/static/common/images/Logo.png
xnat_dashboards/app/static/dashboards/css/custom.css
xnat_dashboards/app/static/dashboards/css/custom_bootstrap_overite.css
xnat_dashboards/app/static/dashboards/js/custom.js
xnat_dashboards/app/static/dashboards/js/plotly_chart_generator.js
xnat_dashboards/app/templates/authentication/login.html
xnat_dashboards/app/templates/dashboards/stats_dashboards.html
xnat_dashboards/app/templates/dashboards/stats_dashboards_pp.html
xnat_dashboards/app/templates/dashboards/bbrc/bbrc_test_grid.html
xnat_dashboards/bbrc/__init__.py
xnat_dashboards/bbrc/data_fetcher.py
xnat_dashboards/bbrc/data_filter.py
xnat_dashboards/bbrc/data_formatter.py
xnat_dashboards/data_cleaning/__init__.py
xnat_dashboards/data_cleaning/data_filter.py
xnat_dashboards/data_cleaning/data_formatter.py
xnat_dashboards/data_cleaning/graph_generator.py
xnat_dashboards/pyxnat_interface/__init__.py
xnat_dashboards/pyxnat_interface/data_fetcher.py
xnat_dashboards/pyxnat_interface/pickle_saver.py
xnat_dashboards/tests/__init__.py
xnat_dashboards/tests/test_1_pickle_saver.py
xnat_dashboards/tests/test_app.py
xnat_dashboards/tests/test_d_fetcher.py
xnat_dashboards/tests/test_d_filter.py
xnat_dashboards/tests/test_d_filter_pp.py
xnat_dashboards/tests/test_d_formatter.py
xnat_dashboards/tests/test_d_formatter_pp.py
XNAT_Dashboards-0.3.0.dist-info/LICENSE
XNAT_Dashboards-0.3.0.dist-info/METADATA
XNAT_Dashboards-0.3.0.dist-info/WHEEL
XNAT_Dashboards-0.3.0.dist-info/top_level.txt
XNAT_Dashboards-0.3.0.dist-info/RECORD
