Metadata-Version: 2.1
Name: XNAT-Dashboards
Version: 0.3.0
Summary: XNAT data visualization using Flask and Pyxnat
Home-page: https://pypi.org/project/xnat-dashboards/
Author: Mohammad Asif Hashmi
Author-email: hashmi.masif@gmail.com
License: MIT
Platform: any
Classifier: Intended Audience :: Developers
Classifier: Intended Audience :: Science/Research
Classifier: Intended Audience :: Education
Classifier: License :: OSI Approved :: MIT License
Classifier: Operating System :: OS Independent
Classifier: Topic :: Scientific/Engineering
Classifier: Topic :: Utilities
Classifier: Topic :: Internet :: WWW/HTTP
Classifier: Programming Language :: Python :: 3.6
Requires-Dist: flask
Requires-Dist: flask-wtf
Requires-Dist: pandas
Requires-Dist: pyxnat
Requires-Dist: tqdm
